flywaymigrationconstructmonocdk/__init__.py
flywaymigrationconstructmonocdk/py.typed
flywaymigrationconstructmonocdk/_jsii/__init__.py
flywaymigrationconstructmonocdk/_jsii/flywaymigrationconstructmonocdk@0.0.4.jsii.tgz
flywaymigrationconstructmonocdk-0.0.4.dist-info/LICENSE
flywaymigrationconstructmonocdk-0.0.4.dist-info/METADATA
flywaymigrationconstructmonocdk-0.0.4.dist-info/WHEEL
flywaymigrationconstructmonocdk-0.0.4.dist-info/top_level.txt
flywaymigrationconstructmonocdk-0.0.4.dist-info/RECORD
