Metadata-Version: 2.1
Name: flywaymigrationconstructmonocdk
Version: 0.0.4
Summary: flywaymigrationconstructmonocdk
Home-page: https://github.com/180517/flywaymigrationconstruct-monocdk.git
Author: APrzysiuda<180517@umons.ac.be>
License: Apache-2.0
Project-URL: Source, https://github.com/180517/flywaymigrationconstruct-monocdk.git
Platform: UNKNOWN
Classifier: Intended Audience :: Developers
Classifier: Operating System :: OS Independent
Classifier: Programming Language :: JavaScript
Classifier: Programming Language :: Python :: 3 :: Only
Classifier: Programming Language :: Python :: 3.6
Classifier: Programming Language :: Python :: 3.7
Classifier: Programming Language :: Python :: 3.8
Classifier: Programming Language :: Python :: 3.9
Classifier: Typing :: Typed
Classifier: Development Status :: 5 - Production/Stable
Classifier: License :: OSI Approved
Requires-Python: >=3.6
License-File: LICENSE
Requires-Dist: constructs (<4.0.0,>=3.2.27)
Requires-Dist: jsii (<2.0.0,>=1.36.0)
Requires-Dist: monocdk (<2.0.0,>=1.128.0)
Requires-Dist: publication (>=0.0.3)
